{"stats":{"minecraft:custom":{"minecraft:time_since_rest":824808,"minecraft:sprint_one_cm":205277,"minecraft:walk_one_cm":1926249,"minecraft:mob_kills":1,"minecraft:drop":4,"minecraft:damage_dealt":100,"minecraft:swim_one_cm":1077,"minecraft:fly_one_cm":2544910,"minecraft:open_chest":13,"minecraft:crouch_one_cm":110299,"minecraft:play_time":824808,"minecraft:sneak_time":35633,"minecraft:walk_under_water_one_cm":220156,"minecraft:jump":2122,"minecraft:leave_game":22,"minecraft:walk_on_water_one_cm":43995,"minecraft:time_since_death":824808,"minecraft:total_world_time":842684},"minecraft:dropped":{"minecraft:quartz_stairs":1,"minecraft:smooth_quartz":1,"fairylights:triangle_pennant":2},"minecraft:picked_up":{"minecraft:barrier":1,"minecraft:water_bucket":1,"minecraft:lava_bucket":1,"minecraft:soul_torch":1,"fairylights:triangle_pennant":2,"cfm:white_picket_gate":1,"minecraft:soul_lantern":1,"minecraft:quartz_stairs":2,"fairylights:oil_lantern":1},"minecraft:used":{"minecraft:polished_deepslate_stairs":1,"minecraft:shroomlight":76,"minecraft:quartz_bricks":27,"minecraft:glass":1889,"minecraft:black_wool":7,"minecraft:water_bucket":104,"minecraft:sea_lantern":64,"minecraft:lava_bucket":87,"automobility:dash_panel":18,"minecraft:polished_granite_stairs":1,"minecraft:enchanting_table":1,"minecraft:quartz_pillar":2,"minecraft:crying_obsidian":73,"minecraft:black_stained_glass_pane":257,"minecraft:yellow_stained_glass":12,"minecraft:red_concrete":3,"minecraft:grass_block":95,"minecraft:red_stained_glass":2,"minecraft:barrier":617,"minecraft:jungle_log":4,"minecraft:polished_andesite_stairs":1,"minecraft:quartz_block":14,"minecraft:chest":10,"minecraft:white_terracotta":8,"minecraft:smooth_quartz":215,"minecraft:redstone_block":4,"fairylights:oil_lantern":2,"minecraft:quartz_stairs":20,"minecraft:cobblestone_slab":34,"minecraft:soul_lantern":26,"minecraft:smooth_quartz_stairs":52,"minecraft:gilded_blackstone":1,"minecraft:torch":1,"minecraft:soul_sand":13,"minecraft:cobblestone":17,"minecraft:black_stained_glass":2383,"minecraft:emerald_block":34,"minecraft:crafting_table":1,"minecraft:stripped_oak_wood":121,"minecraft:prismarine_brick_stairs":40,"minecraft:andesite_stairs":1,"minecraft:pink_stained_glass":4,"minecraft:gold_block":1,"minecraft:polished_diorite_stairs":1,"minecraft:pearlescent_froglight":69,"minecraft:cobbled_deepslate_stairs":1,"minecraft:jukebox":1,"minecraft:deepslate_brick_stairs":1,"minecraft:stripped_spruce_log":4,"cfm:white_picket_gate":25,"minecraft:soul_torch":16,"minecraft:diorite_stairs":1}},"DataVersion":3465}